zlig/__init__.py
zlig/_version.py
zlig/_wheels.py
zlig/build.zig.jinja2
zlig-0.0.0.dist-info/LICENSE
zlig-0.0.0.dist-info/WHEEL
zlig-0.0.0.dist-info/METADATA
zlig-0.0.0.dist-info/RECORD
