Metadata-Version: 2.1
Name: zlig
Version: 0.0.0
Summary: Binary wheel support based on Flit.
Author-email: Tzu-ping Chung <uranusjr@gmail.com>
Requires-Python: >=3.8
Classifier: License :: OSI Approved :: MIT License
Requires-Dist: flit_core >=3.2,<4
Requires-Dist: jinja2 >3
Requires-Dist: packaging >=19.1
Requires-Dist: packaging-dists >= 0.3
Requires-Dist: toml
Requires-Dist: ziglang >=0.8.0
Project-URL: Home, https://github.com/uranusjr/zlig
